<root>
  <styles>
    <include src="s2r://panorama/styles/gamestyles.vcss_c" />
    <include src="s2r://panorama/styles/dac_global.vcss_c" />
    <include src="s2r://panorama/styles/dac_ui_tutorial.vcss_c" />
  </styles>

  <snippets>
  </snippets>

  <DACUITutorial class="TutorialPanel" hittest="false">
    <Panel id="Panel_TopMiddle" class="BevelPanel">
      <Label id="Tutorial_Text_TopMiddle" text="{s:tutorial_text}" hittest="false" />
      <Panel id="ArrowNext_TopMiddle" class="Arrow_Next" />
    </Panel>
    <Panel id="Panel_BottomMiddle" class="BevelPanel">
      <Label id="Tutorial_Text_BottomMiddle" text="{s:tutorial_text}" hittest="false" />
      <Panel id="ArrowNext_BottomMiddle" class="Arrow_Next" />
    </Panel>    
    <Panel id="ScreenBlank" hittest="false">
    </Panel>
    <Panel id="Arrow_PlaceUnit" hittest="false"/>
    <Panel id="Arrow_HudShop" hittest="false"/>
    <Panel id="Arrow_Shop" hittest="false"/>
    <Panel id="Arrow_ItemTab" hittest="false"/>
    <Panel id="Arrow_Reroll" hittest="false"/>
  </DACUITutorial>
</root>