<root>
	<styles>
		<include src="s2r://panorama/styles/gamestyles.vcss_c" />
		<include src="s2r://panorama/styles/popups/popups_shared.vcss_c" />
		<include src="s2r://panorama/styles/popups/popup_generic.vcss_c" />
		<include src="s2r://panorama/styles/popups/popup_battlepass_progress.vcss_c" />
		<include src="s2r://panorama/styles/dac_ui_battlepass_level.vcss_c" />
		<include src="s2r://panorama/styles/dac_db_control_battlepass_rewardline.vcss_c" />
	</styles>

	<PopupBattlepassProgress class="PopupPanel" popupbackground="blur">
		<Panel id="CloseBG" hittest="true" onactivate="UIPopupButtonClicked( close )" />

		<Panel id="Body" hittest="true">

			<DACBattlePassRewardLine id="BattlepassRewardLine"/>
			
			<Panel id="ContinueButton" onactivate="UIPopupButtonClicked( close )" />
		</Panel>

	</PopupBattlepassProgress>
</root>
